duanxin.py
duanxin_package-0.1.dist-info/METADATA
duanxin_package-0.1.dist-info/WHEEL
duanxin_package-0.1.dist-info/top_level.txt
duanxin_package-0.1.dist-info/RECORD
