Metadata-Version: 2.1
Name: duanxin-package
Version: 0.1
Summary: A package to increment numbers by 1
Author: Lin p
Author-email: L_hp777@163.com
